avython/__init__.py
avython/__init__.pyc
avython/__pycache__/__init__.cpython-34.pyc
avython/__pycache__/__init__.cpython-36.pyc
avython/console/__init__.py
avython/console/__init__.pyc
avython/console/main.py
avython/console/main.pyc
avython/console/__pycache__/__init__.cpython-34.pyc
avython/console/__pycache__/__init__.cpython-36.pyc
avython/console/__pycache__/main.cpython-34.pyc
avython/console/__pycache__/main.cpython-36.pyc
avython/download/__init__.py
avython/download/__init__.pyc
avython/download/driver.py
avython/download/driver.pyc
avython/download/main.py
avython/download/main.pyc
avython/download/s3.py
avython/download/s3.pyc
avython/download/wget.py
avython/download/wget.pyc
avython/download/__pycache__/__init__.cpython-34.pyc
avython/download/__pycache__/__init__.cpython-36.pyc
avython/download/__pycache__/driver.cpython-34.pyc
avython/download/__pycache__/driver.cpython-36.pyc
avython/download/__pycache__/main.cpython-34.pyc
avython/download/__pycache__/main.cpython-36.pyc
avython/download/__pycache__/wget.cpython-34.pyc
avython/download/__pycache__/wget.cpython-36.pyc
avython/gitautotag/__init__.py
avython/gitautotag/__init__.pyc
avython/gitautotag/gitautotag.py
avython/gitautotag/gitautotag.pyc
avython/gitautotag/main.pyc
avython/gitautotag/__pycache__/__init__.cpython-34.pyc
avython/gitautotag/__pycache__/__init__.cpython-36.pyc
avython/gitautotag/__pycache__/gitautotag.cpython-34.pyc
avython/gitautotag/__pycache__/gitautotag.cpython-36.pyc
avython/gitautotag/__pycache__/main.cpython-34.pyc
avython-0.0.7.data/scripts/gitautotag.py
avython-0.0.7.dist-info/DESCRIPTION.rst
avython-0.0.7.dist-info/METADATA
avython-0.0.7.dist-info/RECORD
avython-0.0.7.dist-info/WHEEL
avython-0.0.7.dist-info/entry_points.txt
avython-0.0.7.dist-info/metadata.json
avython-0.0.7.dist-info/top_level.txt
tests/__init__.py
tests/test_download.py
tests/test_gitautotag.py
tests/runtests/__init__.py
tests/tmp/__init__.py
