Metadata-Version: 2.0
Name: avython
Version: 0.0.7
Summary: Common resources to extend python code
Home-page: https://github.com/avara1986/avython.git
Author: Alberto Vara
Author-email: a.vara.1986@gmail.com
License: MIT
Keywords: avython
Platform: any
Classifier: Development Status :: 4 - Beta
Classifier: Environment :: Console
Classifier: Intended Audience :: Developers
Classifier: Natural Language :: English
Classifier: License :: OSI Approved :: MIT License
Classifier: Operating System :: OS Independent
Classifier: Programming Language :: Python
Classifier: Programming Language :: Python :: 2
Classifier: Programming Language :: Python :: 3
Requires-Dist: awscli
Requires-Dist: pathlib
